<?xml version="1.0" encoding="utf-8" ?>
<LearningStandardItem RefId="1AEDC1B877DE4910A0ED8474D9A1092F" xml:lang="en">				
	<StandardHierarchyLevel>
		<Number>5</Number>
		<Description>Standard</Description>
	</StandardHierarchyLevel>
	<PredecessorItems>
		<LearningStandardItemRefId>2ABAD306C29949F899683A13FFC985BE</LearningStandardItemRefId>
	</PredecessorItems>
	<StatementCodes>
		<StatementCode>Mathematics.S.MD.1.2</StatementCode>
	</StatementCodes>
	<Statements>
		<Statement>(+) Calculate the expected value of a random variable; interpret it as the mean of the probability distribution.</Statement>
	</Statements>
	<GradeLevels>
		<GradeLevel>HS</GradeLevel>
	</GradeLevels>
	<LearningStandardDocumentRefId>B62C1C106873438AA0126760075A65A3</LearningStandardDocumentRefId>
</LearningStandardItem> 