<?xml version="1.0" encoding="utf-8" ?>
<LearningStandardItem RefId="2ABAD306C29949F899683A13FFC985BE" xml:lang="en">				
	<StandardHierarchyLevel>
		<Number>4</Number>
		<Description>Cluster</Description>
	</StandardHierarchyLevel>
	<PredecessorItems>
		<LearningStandardItemRefId>B4A0D11C615D49BAA44EB5612F9D3D7B</LearningStandardItemRefId>
	</PredecessorItems>
	<StatementCodes>
		<StatementCode>Mathematics.S.MD</StatementCode>
	</StatementCodes>
	<Statements>
		<Statement>Calculate expected values and use them to solve problems.</Statement>
	</Statements>
	<GradeLevels>
		<GradeLevel>HS</GradeLevel>
	</GradeLevels>
	<LearningStandardDocumentRefId>B62C1C106873438AA0126760075A65A3</LearningStandardDocumentRefId>
</LearningStandardItem> 