<?xml version="1.0" encoding="utf-8" ?>
<LearningStandardItem RefId="91FABAB899814C55851003A0EE98F8FB" xml:lang="en">
  <StandardHierarchyLevel>
    <Number>4</Number>
    <Description>Cluster</Description>
  </StandardHierarchyLevel>
  <PredecessorItems>
    <LearningStandardItemRefId>21BC61722C06499D878EBA86D78B9384</LearningStandardItemRefId>
  </PredecessorItems>
  <StatementCodes>
    <StatementCode>Mathematics.6.RP.1</StatementCode>
  </StatementCodes>
  <Statements>
    <Statement>Understand ratio concepts and use ratio reasoning to solve problems.</Statement>
  </Statements>
  <GradeLevels>
    <GradeLevel>6</GradeLevel>
  </GradeLevels>
  <LearningStandardDocumentRefId>B62C1C106873438AA0126760075A65A3</LearningStandardDocumentRefId>
</LearningStandardItem>
