<?xml version="1.0" encoding="utf-8" ?>
<LearningStandardItem RefId="5794EA49CA164E6B981C2E33A6983048" xml:lang="en">
	<StandardSettingBody>
		<Country>US</Country>
		<SettingBodyName>NGA and CCSSO</SettingBodyName>
	</StandardSettingBody>
	<StandardHierarchyLevel>
		<Number>3</Number>
		<Description>Standard Item</Description>
	</StandardHierarchyLevel>
	<PredecessorItems>
		<LearningStandardItemRefId>0BD09B34635542C28B91E1A8ABCC8952</LearningStandardItemRefId>
	</PredecessorItems>
	<StatementCodes>
		<StatementCode>W.5.10</StatementCode>
	</StatementCodes>
	<Statements>
		<Statement>
			Write routinely over extended time frames (time for research, reflection, and revision) and shorter time frames (a single sitting or a day or two) for a range of discipline-specific tasks, purposes, and audiences.
		</Statement>
	</Statements>
	<GradeLevels>
		<GradeLevel>
			<Code>05</Code>
		</GradeLevel>
	</GradeLevels>
	<SubjectArea>
		<Code>01</Code>
		<OtherCodeList>
			<OtherCode Codeset="Text">English Language Arts &amp; Literacy</OtherCode>
		</OtherCodeList>
	</SubjectArea>
	<StandardIdentifier>
		<YearCreated>2010</YearCreated>
		<SubjectArea>
			<Code>01</Code>
			<OtherCodeList>
				<OtherCode Codeset="Text">English Language Arts &amp; Literacy</OtherCode>
			</OtherCodeList>
		</SubjectArea>
		<StandardNumber>01</StandardNumber>
		<GradeLevels>
			<GradeLevel>
				<Code>KG</Code>
			</GradeLevel>
			<GradeLevel>
				<Code>01</Code>
			</GradeLevel>
			<GradeLevel>
				<Code>02</Code>
			</GradeLevel>
			<GradeLevel>
				<Code>03</Code>
			</GradeLevel>
			<GradeLevel>
				<Code>04</Code>
			</GradeLevel>
			<GradeLevel>
				<Code>05</Code>
			</GradeLevel>
			<GradeLevel>
				<Code>06</Code>
			</GradeLevel>
			<GradeLevel>
				<Code>07</Code>
			</GradeLevel>
			<GradeLevel>
				<Code>08</Code>
			</GradeLevel>
			<GradeLevel>
				<Code>09</Code>
			</GradeLevel>
			<GradeLevel>
				<Code>10</Code>
			</GradeLevel>
			<GradeLevel>
				<Code>11</Code>
			</GradeLevel>
			<GradeLevel>
				<Code>12</Code>
			</GradeLevel>
		</GradeLevels>
		<Organization>NGA and CCSSO</Organization>
	</StandardIdentifier>
	<LearningStandardDocumentRefId>0D46CE88E57C4670A60E82E181CF152D</LearningStandardDocumentRefId>

</LearningStandardItem>




