<?xml version="1.0" encoding="utf-8" ?>
<LearningStandardItem RefId="D5C6CCF16B584416909E1E2023EE9AE1" xml:lang="en">
  <StandardHierarchyLevel>
    <Number>6</Number>
    <Description>Standard</Description>
  </StandardHierarchyLevel>
  <PredecessorItems>
    <LearningStandardItemRefId>D7820F1DBC7C42acBFD6B0BB451914C2</LearningStandardItemRefId>
  </PredecessorItems>
  <StatementCodes>
    <StatementCode>ELA.CC.3.RF.4.b</StatementCode>
  </StatementCodes>
  <Statements>
    <Statement> Fluency: Read grade-level prose and poetry orally with accuracy, appropriate rate, and expression.</Statement>
  </Statements>
  <GradeLevels>
    <GradeLevel>3</GradeLevel>
  </GradeLevels>
  <SubjectArea>ELA</SubjectArea>
  <DocumentStatus>Adopted</DocumentStatus>
  <DocumentDate>24052011</DocumentDate>
  <LearningStandardDocumentRefId>0FAC40650F514a459951A657F942B845</LearningStandardDocumentRefId>

</LearningStandardItem>