<?xml version="1.0" encoding="utf-8" ?>
<LearningStandardItem RefId="88C47D1E51D84a81ABA1008691A01CF9" xml:lang="en">
  <StandardHierarchyLevel>
    <Number>6</Number>
    <Description>Standard</Description>
  </StandardHierarchyLevel>
  <PredecessorItems>
    <LearningStandardItemRefId>C34A7209EE3E4969AA850420FEC6523F</LearningStandardItemRefId>
  </PredecessorItems>
  <StatementCodes>
    <StatementCode>ELA.CC.1.L.1.g</StatementCode>
  </StatementCodes>
  <Statements>
    <Statement>Conventions of Standard English:Use frequently occurring conjunctions (e.g., and, but, or, so, because).</Statement>
  </Statements>
  <GradeLevels>
    <GradeLevel>1</GradeLevel>
  </GradeLevels>
  <SubjectArea>ELA</SubjectArea>
  <DocumentStatus>Adopted</DocumentStatus>
  <DocumentDate>24052011</DocumentDate>
  <LearningStandardDocumentRefId>0FAC40650F514a459951A657F942B845</LearningStandardDocumentRefId>
 
</LearningStandardItem>