<?xml version="1.0" encoding="utf-8" ?>
<LearningStandardItem RefId="B6331A8CE422488c82A6FEFCC557C929" xml:lang="en">
  <StandardHierarchyLevel>
    <Number>6</Number>
    <Description>Standard</Description>
  </StandardHierarchyLevel>
  <PredecessorItems>
    <LearningStandardItemRefId>DC38A9549D2D44a6B20F2E1D8D49D265</LearningStandardItemRefId>
  </PredecessorItems>
  <StatementCodes>
    <StatementCode>ELA.CC.4.W.3.b</StatementCode>
  </StatementCodes>
  <Statements>
    <Statement>
      Text Types and Purposes: Use dialogue and description to develop experiences and events or show the responses of characters to situations.
    </Statement>
  </Statements>
  <GradeLevels>
    <GradeLevel>4</GradeLevel>
  </GradeLevels>
  <SubjectArea>ELA</SubjectArea>
  <DocumentStatus>Adopted</DocumentStatus>
  <DocumentDate>24052011</DocumentDate>
  <LearningStandardDocumentRefId>0FAC40650F514a459951A657F942B845</LearningStandardDocumentRefId>
</LearningStandardItem>