<?xml version="1.0" encoding="utf-8" ?>
<LearningStandardItem RefId="743A3FB1E45B4a82A91820A4DA97568D" xml:lang="en">
  <StandardHierarchyLevel>
    <Number>6</Number>
    <Description>Standard</Description>
  </StandardHierarchyLevel>
  <PredecessorItems>
    <LearningStandardItemRefId>A792CADBA39144b8B9033AF5FA4D5D79</LearningStandardItemRefId>
  </PredecessorItems>
  <StatementCodes>
    <StatementCode>ELA.CC.4.L.4.a</StatementCode>
  </StatementCodes>
  <Statements>
    <Statement> Vocabulary Acquisition and Use:Use context (e.g., definitions, examples, or restatements in text) as a clue to the meaning of a word or phrase.</Statement>
  </Statements>
  <GradeLevels>
    <GradeLevel>4</GradeLevel>
  </GradeLevels>
  <SubjectArea>ELA</SubjectArea>
  <DocumentStatus>Adopted</DocumentStatus>
  <DocumentDate>24052011</DocumentDate>
  <LearningStandardDocumentRefId>0FAC40650F514a459951A657F942B845</LearningStandardDocumentRefId>
 
</LearningStandardItem>