<?xml version="1.0" encoding="utf-8" ?>
<LearningStandardItem RefId="FD5CF800EFC24a388C73C081FF49F539" xml:lang="en">
  <StandardHierarchyLevel>
    <Number>5</Number>
    <Description>Standard</Description>
  </StandardHierarchyLevel>
  <PredecessorItems>
    <LearningStandardItemRefId>D69C12DADF1743e3AB4E645BB71679EA</LearningStandardItemRefId>
  </PredecessorItems>
  <StatementCodes>
    <StatementCode>ELA.CC.11-12.RI.9</StatementCode>
  </StatementCodes>
  <Statements>
    <Statement>
      Integration of Knowledge and Ideas: Analyze seventeenth-, eighteenth-, and nineteenth-century foundational U.S. documents of historical and literary significance (including The Declaration of Independence, the Preamble to the Constitution, the Bill of Rights, and Lincoln’s Second Inaugural Address) for their themes, purposes, and rhetorical features.
    </Statement>
  </Statements>
  <GradeLevels>
    <GradeLevel>11-12</GradeLevel>
  </GradeLevels>
  <SubjectArea>ELA</SubjectArea>
  <DocumentStatus>Adopted</DocumentStatus>
  <DocumentDate>24052011</DocumentDate>
  <LearningStandardDocumentRefId>0FAC40650F514a459951A657F942B845</LearningStandardDocumentRefId>

</LearningStandardItem>