<?xml version="1.0" encoding="utf-8" ?>
<LearningStandardItem RefId="25C9ADEF2AB949e6A350EAAA4BE3BDD5" xml:lang="en">
  <StandardHierarchyLevel>
    <Number>6</Number>
    <Description>Standard</Description>
  </StandardHierarchyLevel>
  <PredecessorItems>
    <LearningStandardItemRefId>8BB95956E60A461c913F91256043CF60</LearningStandardItemRefId>
  </PredecessorItems>
  <StatementCodes>
    <StatementCode>ELA.CC.8.L.4.d</StatementCode>
  </StatementCodes>
  <Statements>
    <Statement> Verify the preliminary determination of the meaning of a word or phrase (e.g., by checking the inferred meaning in context or in a dictionary).</Statement>
  </Statements>
  <GradeLevels>
    <GradeLevel>8</GradeLevel>
  </GradeLevels>
  <SubjectArea>ELA</SubjectArea>
  <DocumentStatus>Adopted</DocumentStatus>
  <DocumentDate>24052011</DocumentDate>
  <LearningStandardDocumentRefId>0FAC40650F514a459951A657F942B845</LearningStandardDocumentRefId>
  <Level4> Vocabulary Acquisition and Use</Level4>
</LearningStandardItem>