<?xml version="1.0" encoding="utf-8" ?>
<LearningStandardItem RefId="4C075C2A234E40058E4B16E7F40E813E" xml:lang="en">
  <StandardHierarchyLevel>
    <Number>5</Number>
    <Description>Standard</Description>
  </StandardHierarchyLevel>
  <PredecessorItems>
    <LearningStandardItemRefId>88E5229307974f0e958F7300DED5BC6B</LearningStandardItemRefId>
  </PredecessorItems>
  <StatementCodes>
    <StatementCode>ELA.CC.8.RI.1</StatementCode>
  </StatementCodes>
  <Statements>
    <Statement>
      Key Ideas and Details: Cite the textual evidence that most strongly supports an analysis of what the text says explicitly as well as inferences drawn from the text.
    </Statement>
  </Statements>
  <GradeLevels>
    <GradeLevel>8</GradeLevel>
  </GradeLevels>
  <SubjectArea>ELA</SubjectArea>
  <DocumentStatus>Adopted</DocumentStatus>
  <DocumentDate>24052011</DocumentDate>
  <LearningStandardDocumentRefId>0FAC40650F514a459951A657F942B845</LearningStandardDocumentRefId>
</LearningStandardItem>