<?xml version="1.0" encoding="utf-8" ?>

<LearningStandardItem RefId="6F4455B55B4240F3B4738DD9DB3EAF40" xml:lang="en">				
	<StandardHierarchyLevel>
		<Number>5</Number>
		<Description>Standard</Description>
	</StandardHierarchyLevel>
	<PredecessorItems>
		<LearningStandardItemRefId>BB49D28AFFFE46FBB8F4ECA58C88B001</LearningStandardItemRefId>
	</PredecessorItems>
	<StatementCodes>
		<StatementCode>Mathematics.K.CC.2.5</StatementCode>
	</StatementCodes>
	<Statements>
		<Statement>Count to answer "how many?" questions about as many as 20 things arranged in a line, a rectangular array, or a circle, or as many as 10 things in a scattered configuration; given a number from 1-20, count out that many objects</Statement>
	</Statements>
	<GradeLevels>
		<GradeLevel>K</GradeLevel>
	</GradeLevels>
	<LearningStandardDocumentRefId>B62C1C106873438AA0126760075A65A3</LearningStandardDocumentRefId>
</LearningStandardItem> 