<?xml version="1.0" encoding="utf-8" ?>

<LearningStandardItem RefId="3364A2D8B7654D3696223F2F3E2CD406" xml:lang="en">				
	<StandardHierarchyLevel>
		<Number>5</Number>
		<Description>Standard</Description>
	</StandardHierarchyLevel>
	<PredecessorItems>
		<LearningStandardItemRefId>20163EF6BD26432AA11A2E0E37083DE9</LearningStandardItemRefId>
	</PredecessorItems>
	<StatementCodes>
		<StatementCode>Mathematics.G.GPE.1.1</StatementCode>
	</StatementCodes>
	<Statements>
		<Statement>Derive the equation of a circle of given center and radius using the Pythagorean Theorem; complete the square to find the center and radius of a circle given by an equation.</Statement>
	</Statements>
	<GradeLevels>
		<GradeLevel>HS</GradeLevel>
	</GradeLevels>
	<LearningStandardDocumentRefId>B62C1C106873438AA0126760075A65A3</LearningStandardDocumentRefId>
</LearningStandardItem>